odoo/addons/partner_duns/README.rst
odoo/addons/partner_duns/__init__.py
odoo/addons/partner_duns/__manifest__.py
odoo/addons/partner_duns/i18n/partner_duns.pot
odoo/addons/partner_duns/models/__init__.py
odoo/addons/partner_duns/models/res_partner.py
odoo/addons/partner_duns/readme/CONTRIBUTORS.rst
odoo/addons/partner_duns/readme/DESCRIPTION.rst
odoo/addons/partner_duns/static/description/icon.png
odoo/addons/partner_duns/static/description/index.html
odoo/addons/partner_duns/tests/__init__.py
odoo/addons/partner_duns/tests/test_partner_duns.py
odoo/addons/partner_duns/views/res_partner.xml
odoo14_addon_partner_duns-14.0.1.0.1.dist-info/METADATA
odoo14_addon_partner_duns-14.0.1.0.1.dist-info/WHEEL
odoo14_addon_partner_duns-14.0.1.0.1.dist-info/top_level.txt
odoo14_addon_partner_duns-14.0.1.0.1.dist-info/RECORD
